llama_index/retrievers/you/__init__.py
llama_index/retrievers/you/base.py
llama_index_retrievers_you-1.0.0.dist-info/METADATA
llama_index_retrievers_you-1.0.0.dist-info/WHEEL
llama_index_retrievers_you-1.0.0.dist-info/licenses/LICENSE
llama_index_retrievers_you-1.0.0.dist-info/RECORD
