Metadata-Version: 2.4
Name: llama-index-retrievers-you
Version: 1.0.0
Summary: llama-index retrievers you integration
Author-email: akhil@you.com
License-Expression: MIT
License-File: LICENSE
Requires-Python: <4.0,>=3.9
Requires-Dist: httpx>=0.27.0
Requires-Dist: llama-index-core<0.15,>=0.13.0
